MyPakage/MyPakage.py
MyPakage/__init__.py
MyPakage-0.2.8.dist-info/LICENSE
MyPakage-0.2.8.dist-info/METADATA
MyPakage-0.2.8.dist-info/WHEEL
MyPakage-0.2.8.dist-info/top_level.txt
MyPakage-0.2.8.dist-info/RECORD
