Metadata-Version: 2.1
Name: MyPakage
Version: 0.2.8
Summary: this code is used for my learning, because other wheels are not enough or perfect author:nwkami
Home-page: https://github.com/yourusername/my-awesome-package
Author: nwkami
Author-email: your.email@example.com
License: MIT
Classifier: Development Status :: 3 - Alpha
Classifier: Intended Audience :: Developers
Classifier: License :: OSI Approved :: MIT License
Classifier: Programming Language :: Python
Classifier: Programming Language :: Python :: 3
Classifier: Programming Language :: Python :: 3.6
Classifier: Programming Language :: Python :: 3.7
Classifier: Programming Language :: Python :: 3.8
Classifier: Programming Language :: Python :: 3.9
License-File: LICENSE
Requires-Dist: setuptools
Requires-Dist: numpy (~=1.25.2)
Requires-Dist: imageio (~=2.31.1)
Requires-Dist: Pillow (~=10.0.0)
Requires-Dist: geographiclib (~=2.0)
Requires-Dist: geopy
